odoo/addons/sale_order_report_customer_lead/README.rst
odoo/addons/sale_order_report_customer_lead/__init__.py
odoo/addons/sale_order_report_customer_lead/__manifest__.py
odoo/addons/sale_order_report_customer_lead/i18n/sale_order_report_customer_lead.pot
odoo/addons/sale_order_report_customer_lead/readme/CONTRIBUTORS.rst
odoo/addons/sale_order_report_customer_lead/readme/DESCRIPTION.rst
odoo/addons/sale_order_report_customer_lead/reports/templates.xml
odoo/addons/sale_order_report_customer_lead/static/description/icon.png
odoo/addons/sale_order_report_customer_lead/static/description/index.html
odoo_addon_sale_order_report_customer_lead-15.0.1.0.1.1.dist-info/METADATA
odoo_addon_sale_order_report_customer_lead-15.0.1.0.1.1.dist-info/WHEEL
odoo_addon_sale_order_report_customer_lead-15.0.1.0.1.1.dist-info/top_level.txt
odoo_addon_sale_order_report_customer_lead-15.0.1.0.1.1.dist-info/RECORD
