Metadata-Version: 2.1
Name: odoo-addon-sale-order-report-customer-lead
Version: 15.0.1.0.1.1
Summary: Show the lead time on sale documents
Home-page: https://github.com/OCA/sale-reporting
Author: Camptocamp SA, Odoo Community Association (OCA)
Author-email: support@odoo-community.org
License: AGPL-3
Platform: UNKNOWN
Classifier: Programming Language :: Python
Classifier: Framework :: Odoo
Classifier: Framework :: Odoo :: 15.0
Classifier: License :: OSI Approved :: GNU Affero General Public License v3
Requires-Python: >=3.8
Requires-Dist: odoo <15.1dev,>=15.0a
